resonate/__init__.py
resonate/bridge.py
resonate/coroutine.py
resonate/delay_q.py
resonate/dependencies.py
resonate/graph.py
resonate/options.py
resonate/processor.py
resonate/py.typed
resonate/registry.py
resonate/resonate.py
resonate/scheduler.py
resonate/simulator.py
resonate/utils.py
resonate/clocks/__init__.py
resonate/clocks/step.py
resonate/conventions/__init__.py
resonate/conventions/base.py
resonate/conventions/local.py
resonate/conventions/remote.py
resonate/conventions/sleep.py
resonate/encoders/__init__.py
resonate/encoders/base64.py
resonate/encoders/combined.py
resonate/encoders/header.py
resonate/encoders/json.py
resonate/encoders/jsonpickle.py
resonate/encoders/noop.py
resonate/encoders/pair.py
resonate/errors/__init__.py
resonate/errors/errors.py
resonate/loggers/__init__.py
resonate/loggers/context.py
resonate/loggers/dst.py
resonate/message_sources/__init__.py
resonate/message_sources/local.py
resonate/message_sources/poller.py
resonate/models/__init__.py
resonate/models/callback.py
resonate/models/clock.py
resonate/models/commands.py
resonate/models/context.py
resonate/models/convention.py
resonate/models/durable_promise.py
resonate/models/encoder.py
resonate/models/handle.py
resonate/models/logger.py
resonate/models/message.py
resonate/models/message_source.py
resonate/models/result.py
resonate/models/retry_policy.py
resonate/models/router.py
resonate/models/schedules.py
resonate/models/store.py
resonate/models/task.py
resonate/retry_policies/__init__.py
resonate/retry_policies/constant.py
resonate/retry_policies/exponential.py
resonate/retry_policies/linear.py
resonate/retry_policies/never.py
resonate/routers/__init__.py
resonate/routers/tag.py
resonate/stores/__init__.py
resonate/stores/local.py
resonate/stores/remote.py
resonate_sdk-0.6.7.dist-info/METADATA
resonate_sdk-0.6.7.dist-info/WHEEL
resonate_sdk-0.6.7.dist-info/licenses/LICENSE
resonate_sdk-0.6.7.dist-info/RECORD
