Metadata-Version: 2.4
Name: resonate-sdk
Version: 0.6.7
Summary: Distributed Async Await by Resonate HQ, Inc
Project-URL: Documentation, https://github.com/resonatehq/resonate-sdk-py#readme
Project-URL: Issues, https://github.com/resonatehq/resonate-sdk-py/issues
Project-URL: Source, https://github.com/resonatehq/resonate-sdk-py
Author-email: "Resonate HQ, Inc" <contact@resonatehq.io>
License-File: LICENSE
Requires-Python: >=3.12
Requires-Dist: croniter<7,>=6.0.0
Requires-Dist: jsonpickle<5,>=4
Requires-Dist: requests<3,>=2
